bunnycdn_storage/__init__.py
bunnycdn_storage/bunnycdn_storage.py
bunnycdn_storage-0.4.dist-info/LICENSE
bunnycdn_storage-0.4.dist-info/METADATA
bunnycdn_storage-0.4.dist-info/WHEEL
bunnycdn_storage-0.4.dist-info/top_level.txt
bunnycdn_storage-0.4.dist-info/RECORD
