Metadata-Version: 2.1
Name: bunnycdn-storage
Version: 0.4
Summary: A python module for the BunnyCDN Storage API
Home-page: https://github.com/ajacobsen/bunnycdn-storage
Author: Andy Jacobsen
Author-email: atze.danjo@gmail.com
License: GPLv3+
Platform: UNKNOWN
Requires-Dist: requests
